G_plot/__init__.py
G_plot-1.0.0.dist-info/LICENCE.txt
G_plot-1.0.0.dist-info/METADATA
G_plot-1.0.0.dist-info/WHEEL
G_plot-1.0.0.dist-info/top_level.txt
G_plot-1.0.0.dist-info/RECORD
