Metadata-Version: 2.1
Name: G-plot
Version: 1.0.0
Summary: ploat chart with gsheet
Home-page: UNKNOWN
Author: HSD
Author-email: ashuhemantsingh@gmail.com
License: UNKNOWN
Platform: UNKNOWN
Classifier: Programming Language :: Python :: 3
Classifier: License :: OSI Approved :: MIT License
Classifier: Operating System :: OS Independent
Requires-Python: >=3.6
License-File: LICENCE.txt
